meaning.py
meaning_eraser-0.0.1.dist-info/LICENSE.txt
meaning_eraser-0.0.1.dist-info/METADATA
meaning_eraser-0.0.1.dist-info/WHEEL
meaning_eraser-0.0.1.dist-info/top_level.txt
meaning_eraser-0.0.1.dist-info/RECORD
